{
  "project_info": {
    "project_number": "707331968753",
    "firebase_url": "https://pickappcands.firebaseio.com",
    "project_id": "pickappcands",
    "storage_bucket": "pickappcands.appspot.com"
  },
  "client": [
    {
      "client_info": {
        "mobilesdk_app_id": "1:707331968753:android:b6faa064d33d8598",
        "android_client_info": {
          "package_name": "farm.pickapp.candidates"
        }
      },
      "oauth_client": [
        {
          "client_id": "707331968753-je7b4t5ceauaiffsf9j9tlt467hk0hr5.apps.googleusercontent.com",
          "client_type": 3
        }
      ],
      "api_key": [
        {
          "current_key": "AIzaSyDDgoMDkurECCVNcqWuFq-v-OuAh6bh0FQ"
        }
      ],
      "services": {
        "analytics_service": {
          "status": 1
        },
        "appinvite_service": {
          "status": 1,
          "other_platform_oauth_client": []
        },
        "ads_service": {
          "status": 2
        }
      }
    }
  ],
  "configuration_version": "1"
}